decancer_py-0.4.0.dist-info/METADATA
decancer_py-0.4.0.dist-info/WHEEL
decancer_py-0.4.0.dist-info/license_files/LICENSE
decancer_py/py.typed
decancer_py/__init__.py
decancer_py/decancer_py.pyi
decancer_py/decancer_py.cpython-312-x86_64-linux-gnu.so
decancer_py-0.4.0.dist-info/RECORD
