Metadata-Version: 2.1
Name: decancer_py
Version: 0.4.0
Classifier: License :: OSI Approved :: MIT License
Classifier: Programming Language :: Rust
Classifier: Programming Language :: Python :: Implementation :: CPython
Classifier: Topic :: Software Development :: Libraries :: Python Modules
Classifier: Typing :: Typed
License-File: LICENSE
Summary: Python bindings for decancer.
Keywords: decancer,ffi,string,parsing,unicode
Home-Page: https://github.com/Jonxslays/decancer_py
Author: Jonxslays
License: MIT
Requires-Python: >=3.8, <3.13
Project-URL: homepage, https://github.com/Jonxslays/decancer_py
Project-URL: repository, https://github.com/Jonxslays/decancer_py
Project-URL: documentation, https://github.com/Jonxslays/decancer_py
